pyro/__init__.py
pyro/__main__.py
pyro/argslib.py
pyro/builtins.py
pyro/expressions.py
pyro/lexer.py
pyro/parser.py
pyro/runtime.py
pyro/statements.py
pyrolang-0.1.0.dist-info/METADATA
pyrolang-0.1.0.dist-info/WHEEL
pyrolang-0.1.0.dist-info/entry_points.txt
pyrolang-0.1.0.dist-info/top_level.txt
pyrolang-0.1.0.dist-info/RECORD
